[{"building_code": "APH09", "building_name": "House 09 - Devoke, Graduate College", "usage": "Residential", "year_built": 1996, "floor_area": 1538, "zone": "Alexandra Park", "maze_map_label": [2650], "gas": {"sensor_label": ["Graduate College"], "sensor_uuid": ["APH09_Meter_001"], "usage": 1007.79, "eui": 0.66, "unit": "m3", "eui_annual": 0.66}, "electricity": {"sensor_label": [], "sensor_uuid": [], "usage": null, "eui": null, "unit": "kWh", "eui_annual": null}, "heat": {"sensor_label": [], "sensor_uuid": [], "usage": null, "eui": null, "unit": "MWh", "eui_annual": null}, "water": {"sensor_label": [], "sensor_uuid": [], "usage": null, "eui": null, "unit": "m3", "eui_annual": null}}, {"building_code": "APH10", "building_name": "House 10 - Elterwater, Graduate College", "usage": "Residential", "year_built": 1996, "floor_area": 735, "zone": "Alexandra Park", "maze_map_label": [2651], "gas": {"sensor_label": ["Graduate College"], "sensor_uuid": ["APH10_Meter_003"], "usage": 3990.16, "eui": 5.4, "unit": "m3", "eui_annual": 5.4}, "electricity": {"sensor_label": [], "sensor_uuid": [], "usage": null, "eui": null, "unit": "kWh", "eui_annual": null}, "heat": {"sensor_label": [], "sensor_uuid": [], "usage": null, "eui": null, "unit": "MWh", "eui_annual": null}, "water": {"sensor_label": [], "sensor_uuid": [], "usage": null, "eui": null, "unit": "m3", "eui_annual": null}}, {"building_code": "APH11", "building_name": "House 11 - Ennerdale, Graduate College", "usage": "Residential", "year_built": 1996, "floor_area": 821, "zone": "Alexandra Park", "maze_map_label": [2652], "gas": {"sensor_label": ["Graduate College"], "sensor_uuid": ["APH11_Meter_000"], "usage": 4480.2, "eui": 5.5, "unit": "m3", "eui_annual": 5.5}, "electricity": {"sensor_label": [], "sensor_uuid": [], "usage": null, "eui": null, "unit": "kWh", "eui_annual": null}, "heat": {"sensor_label": [], "sensor_uuid": [], "usage": null, "eui": null, "unit": "MWh", "eui_annual": null}, "water": {"sensor_label": [], "sensor_uuid": [], "usage": null, "eui": null, "unit": "m3", "eui_annual": null}}, {"building_code": "HIC01", "building_name": "Health Innovation One", "usage": "Non Res", "year_built": 2020, "floor_area": 7367, "zone": "Health Innovation Campus", "maze_map_label": [1000138], "gas": {"sensor_label": [], "sensor_uuid": [], "usage": null, "eui": null, "unit": "m3", "eui_annual": null}, "electricity": {"sensor_label": ["Health Innovation Campus"], "sensor_uuid": ["HIC01_Meter_044"], "usage": 734528.0, "eui": 100.0, "unit": "kWh", "eui_annual": 100.0}, "heat": {"sensor_label": ["Health Innovation Campus"], "sensor_uuid": ["HIC01_Meter_042"], "usage": 1214.0, "eui": 0.16, "unit": "MWh", "eui_annual": 0.16}, "water": {"sensor_label": [], "sensor_uuid": [], "usage": null, "eui": null, "unit": "m3", "eui_annual": null}}, {"building_code": "BAILR", "building_name": "Bailrigg House", "usage": "Unknown", "year_built": null, "floor_area": 1223, "zone": "North Campus", "maze_map_label": [2656], "gas": {"sensor_label": ["Bailrigg House"], "sensor_uuid": ["BAILR_Meter_001"], "usage": 7815, "eui": 6.4, "unit": "m3", "eui_annual": 6.4}, "electricity": {"sensor_label": ["Bailrigg House"], "sensor_uuid": ["BAILR_Meter_000"], "usage": 19477.996, "eui": 16.0, "unit": "kWh", "eui_annual": 16.0}, "heat": {"sensor_label": [], "sensor_uuid": [], "usage": null, "eui": null, "unit": "MWh", "eui_annual": null}, "water": {"sensor_label": [], "sensor_uuid": [], "usage": null, "eui": null, "unit": "m3", "eui_annual": null}}, {"building_code": "ROUND", "building_name": "The Roundhouse", "usage": "Non Res", "year_built": 1969, "floor_area": 650, "zone": "North Campus", "maze_map_label": [2657], "gas": {"sensor_label": [], "sensor_uuid": [], "usage": null, "eui": null, "unit": "m3", "eui_annual": null}, "electricity": {"sensor_label": ["The Roundhouse"], "sensor_uuid": ["ROUND_Meter_000"], "usage": 27573, "eui": 42.0, "unit": "kWh", "eui_annual": 42.0}, "heat": {"sensor_label": ["The Roundhouse"], "sensor_uuid": ["ROUND_Meter_003"], "usage": 379.0, "eui": 0.58, "unit": "MWh", "eui_annual": 0.58}, "water": {"sensor_label": [], "sensor_uuid": [], "usage": null, "eui": null, "unit": "m3", "eui_annual": null}}, {"building_code": "BOWLR", "building_name": "Bowland Hall Residences", "usage": "Residential", "year_built": 1992, "floor_area": 6705, "zone": "North Campus", "maze_map_label": [1005716, 1005717, 1005718, 1005719, 1005720, 1005721, 1005722, 1005756, 1005757, 1005758, 1005759, 1005760, 1005762, 2658, 2659], "gas": {"sensor_label": [], "sensor_uuid": [], "usage": null, "eui": null, "unit": "m3", "eui_annual": null}, "electricity": {"sensor_label": ["Bowland Hall"], "sensor_uuid": ["BOWLR_Meter_000"], "usage": 111663, "eui": 17.0, "unit": "kWh", "eui_annual": 17.0}, "heat": {"sensor_label": [], "sensor_uuid": [], "usage": null, "eui": null, "unit": "MWh", "eui_annual": null}, "water": {"sensor_label": [], "sensor_uuid": [], "usage": null, "eui": null, "unit": "m3", "eui_annual": null}}, {"building_code": "GHALL", "building_name": "Great Hall", "usage": "Non Res", "year_built": 1969, "floor_area": 8585, "zone": "North Campus", "maze_map_label": [2661], "gas": {"sensor_label": [], "sensor_uuid": [], "usage": null, "eui": null, "unit": "m3", "eui_annual": null}, "electricity": {"sensor_label": ["Great Hall"], "sensor_uuid": ["GHALL_Meter_005"], "usage": 5, "eui": 0.00058, "unit": "kWh", "eui_annual": 0.00058}, "heat": {"sensor_label": ["Great Hall", "Great Hall"], "sensor_uuid": ["GHALL_Meter_002", "GHALL_Meter_008"], "usage": 3137.0, "eui": 0.37, "unit": "MWh", "eui_annual": 0.37}, "water": {"sensor_label": [], "sensor_uuid": [], "usage": null, "eui": null, "unit": "m3", "eui_annual": null}}, {"building_code": "CSOUT", "building_name": "County South", "usage": "Split Use", "year_built": 1968, "floor_area": 6717, "zone": "North Campus", "maze_map_label": [2662], "gas": {"sensor_label": [], "sensor_uuid": [], "usage": null, "eui": null, "unit": "m3", "eui_annual": null}, "electricity": {"sensor_label": [], "sensor_uuid": [], "usage": null, "eui": null, "unit": "kWh", "eui_annual": null}, "heat": {"sensor_label": ["County South", "County South", "County South"], "sensor_uuid": ["CSOUT_Meter_009", "CSOUT_Meter_012", "CSOUT_Meter_015"], "usage": 4570.0, "eui": 0.68, "unit": "MWh", "eui_annual": 0.68}, "water": {"sensor_label": [], "sensor_uuid": [], "usage": null, "eui": null, "unit": "m3", "eui_annual": null}}, {"building_code": "CJCMN", "building_name": "County John Creed", "usage": "Residential", "year_built": 1991, "floor_area": 4351, "zone": "North Campus", "maze_map_label": [2663, 1005715, 1005714, 1005713, 1005712, 1005711, 1005710], "gas": {"sensor_label": [], "sensor_uuid": [], "usage": null, "eui": null, "unit": "m3", "eui_annual": null}, "electricity": {"sensor_label": [], "sensor_uuid": [], "usage": null, "eui": null, "unit": "kWh", "eui_annual": null}, "heat": {"sensor_label": ["John Creed Residences", "John Creed Residences"], "sensor_uuid": ["CJCMN_Meter_003", "CJCMN_Meter_006"], "usage": 7346.0, "eui": 1.7, "unit": "MWh", "eui_annual": 1.7}, "water": {"sensor_label": [], "sensor_uuid": [], "usage": null, "eui": null, "unit": "m3", "eui_annual": null}}, {"building_code": "BASHH", "building_name": "Bowland ASH House", "usage": "Split Use", "year_built": 1969, "floor_area": 2863, "zone": "North Campus", "maze_map_label": [2688], "gas": {"sensor_label": [], "sensor_uuid": [], "usage": null, "eui": null, "unit": "m3", "eui_annual": null}, "electricity": {"sensor_label": ["Bowland Ash House"], "sensor_uuid": ["BASHH_Meter_012"], "usage": 314818.0, "eui": 110.0, "unit": "kWh", "eui_annual": 110.0}, "heat": {"sensor_label": ["Bowland Ash House", "Bowland Ash House", "Bowland Ash House"], "sensor_uuid": ["BASHH_Meter_002", "BASHH_Meter_005", "BASHH_Meter_008"], "usage": 1586.0, "eui": 0.55, "unit": "MWh", "eui_annual": 0.55}, "water": {"sensor_label": [], "sensor_uuid": [], "usage": null, "eui": null, "unit": "m3", "eui_annual": null}}, {"building_code": "BWNOR", "building_name": "Bowland North", "usage": "Split Use", "year_built": 1967, "floor_area": 7953, "zone": "North Campus", "maze_map_label": [2682], "gas": {"sensor_label": [], "sensor_uuid": [], "usage": null, "eui": null, "unit": "m3", "eui_annual": null}, "electricity": {"sensor_label": ["Bowland North"], "sensor_uuid": ["BWNOR_Meter_001"], "usage": 340282, "eui": 43.0, "unit": "kWh", "eui_annual": 43.0}, "heat": {"sensor_label": ["Bowland North"], "sensor_uuid": ["BWNOR_Meter_008"], "usage": 18327.0, "eui": 2.3, "unit": "MWh", "eui_annual": 2.3}, "water": {"sensor_label": [], "sensor_uuid": [], "usage": null, "eui": null, "unit": "m3", "eui_annual": null}}, {"building_code": "FARAD", "building_name": "Faraday Building", "usage": "Non Res", "year_built": 1970, "floor_area": 5402, "zone": "North Campus", "maze_map_label": [2680], "gas": {"sensor_label": ["Faraday Building"], "sensor_uuid": ["FARAD_Meter_004"], "usage": 0.0, "eui": 0.0, "unit": "m3", "eui_annual": 0.0}, "electricity": {"sensor_label": ["John Creed"], "sensor_uuid": ["FARAD_Meter_029"], "usage": 8784351.0, "eui": 1600.0, "unit": "kWh", "eui_annual": 1600.0}, "heat": {"sensor_label": ["Faraday Building", "Physics Building", "Chemistry Building"], "sensor_uuid": ["FARAD_Meter_015", "FARAD_Meter_031", "FARAD_Meter_036"], "usage": 25415.0, "eui": 4.7, "unit": "MWh", "eui_annual": 4.7}, "water": {"sensor_label": [], "sensor_uuid": [], "usage": null, "eui": null, "unit": "m3", "eui_annual": null}}, {"building_code": "BOWLM", "building_name": "Bowland Main", "usage": "Split Use", "year_built": 1966, "floor_area": 8048, "zone": "North Campus", "maze_map_label": [2783], "gas": {"sensor_label": [], "sensor_uuid": [], "usage": null, "eui": null, "unit": "m3", "eui_annual": null}, "electricity": {"sensor_label": [], "sensor_uuid": [], "usage": null, "eui": null, "unit": "kWh", "eui_annual": null}, "heat": {"sensor_label": ["Bowland Main"], "sensor_uuid": ["BOWLM_Meter_010"], "usage": 0, "eui": 0.0, "unit": "MWh", "eui_annual": 0.0}, "water": {"sensor_label": [], "sensor_uuid": [], "usage": null, "eui": null, "unit": "m3", "eui_annual": null}}, {"building_code": "CHAPL", "building_name": "Chaplaincy Centre", "usage": "Split Use", "year_built": 1970, "floor_area": 1720, "zone": "North Campus", "maze_map_label": [2692], "gas": {"sensor_label": [], "sensor_uuid": [], "usage": null, "eui": null, "unit": "m3", "eui_annual": null}, "electricity": {"sensor_label": ["Chaplaincy Centre"], "sensor_uuid": ["CHAPL_Meter_000"], "usage": 11908, "eui": 6.9, "unit": "kWh", "eui_annual": 6.9}, "heat": {"sensor_label": ["Chaplaincy Centre", "Chaplaincy Centre"], "sensor_uuid": ["CHAPL_Meter_002", "CHAPL_Meter_010"], "usage": 386.0, "eui": 0.22, "unit": "MWh", "eui_annual": 0.22}, "water": {"sensor_label": ["Chaplaincy Centre"], "sensor_uuid": ["CHAPL_Meter_007"], "usage": 0.0, "eui": 0.0, "unit": "m3", "eui_annual": 0.0}}, {"building_code": "SECLO", "building_name": "Security Lodge", "usage": "Non Res", "year_built": 1989, "floor_area": 560, "zone": "North Campus", "maze_map_label": [2694], "gas": {"sensor_label": [], "sensor_uuid": [], "usage": null, "eui": null, "unit": "m3", "eui_annual": null}, "electricity": {"sensor_label": ["Security Lodge"], "sensor_uuid": ["SECLO_Meter_000"], "usage": 82295, "eui": 150.0, "unit": "kWh", "eui_annual": 150.0}, "heat": {"sensor_label": [], "sensor_uuid": [], "usage": null, "eui": null, "unit": "MWh", "eui_annual": null}, "water": {"sensor_label": [], "sensor_uuid": [], "usage": null, "eui": null, "unit": "m3", "eui_annual": null}}, {"building_code": "UNIHO", "building_name": "University House", "usage": "Non Res", "year_built": 1964, "floor_area": 3625, "zone": "North Campus", "maze_map_label": [2697], "gas": {"sensor_label": [], "sensor_uuid": [], "usage": null, "eui": null, "unit": "m3", "eui_annual": null}, "electricity": {"sensor_label": [], "sensor_uuid": [], "usage": null, "eui": null, "unit": "kWh", "eui_annual": null}, "heat": {"sensor_label": ["University House", "University House"], "sensor_uuid": ["UNIHO_Meter_005", "UNIHO_Meter_012"], "usage": 689.0, "eui": 0.19, "unit": "MWh", "eui_annual": 0.19}, "water": {"sensor_label": [], "sensor_uuid": [], "usage": null, "eui": null, "unit": "m3", "eui_annual": null}}, {"building_code": "CENWO", "building_name": "Central Workshops", "usage": "Non Res", "year_built": 1969, "floor_area": 1062, "zone": "North Campus", "maze_map_label": [2713], "gas": {"sensor_label": [], "sensor_uuid": [], "usage": null, "eui": null, "unit": "m3", "eui_annual": null}, "electricity": {"sensor_label": ["Central Workshops"], "sensor_uuid": ["CENWO_Meter_000"], "usage": 83036, "eui": 78.0, "unit": "kWh", "eui_annual": 78.0}, "heat": {"sensor_label": [], "sensor_uuid": [], "usage": null, "eui": null, "unit": "MWh", "eui_annual": null}, "water": {"sensor_label": [], "sensor_uuid": [], "usage": null, "eui": null, "unit": "m3", "eui_annual": null}}, {"building_code": "FURNR", "building_name": "Furness Residences", "usage": "Residential", "year_built": 1992, "floor_area": 10742, "zone": "South Campus", "maze_map_label": [3029, 3031, 3032, 3033, 3034, 2975, 2976, 2977, 2978], "gas": {"sensor_label": [], "sensor_uuid": [], "usage": null, "eui": null, "unit": "m3", "eui_annual": null}, "electricity": {"sensor_label": [], "sensor_uuid": [], "usage": null, "eui": null, "unit": "kWh", "eui_annual": null}, "heat": {"sensor_label": ["Furness Residences", "Furness Residences"], "sensor_uuid": ["FURNR_Meter_001", "FURNR_Meter_007"], "usage": 1768.0, "eui": 0.16, "unit": "MWh", "eui_annual": 0.16}, "water": {"sensor_label": [], "sensor_uuid": [], "usage": null, "eui": null, "unit": "m3", "eui_annual": null}}, {"building_code": "ENECE", "building_name": "Energy Centre", "usage": "Non Res", "year_built": 1966, "floor_area": 927, "zone": "North Campus", "maze_map_label": [3007], "gas": {"sensor_label": [], "sensor_uuid": [], "usage": null, "eui": null, "unit": "m3", "eui_annual": null}, "electricity": {"sensor_label": [], "sensor_uuid": [], "usage": null, "eui": null, "unit": "kWh", "eui_annual": null}, "heat": {"sensor_label": ["Energy Centre"], "sensor_uuid": ["ENECE_Meter_026"], "usage": 2577.0, "eui": 2.8, "unit": "MWh", "eui_annual": 2.8}, "water": {"sensor_label": [], "sensor_uuid": [], "usage": null, "eui": null, "unit": "m3", "eui_annual": null}}, {"building_code": "LIBRA", "building_name": "Library", "usage": "Non Res", "year_built": 1966, "floor_area": 14882, "zone": "North Campus", "maze_map_label": [2704], "gas": {"sensor_label": [], "sensor_uuid": [], "usage": null, "eui": null, "unit": "m3", "eui_annual": null}, "electricity": {"sensor_label": ["Library"], "sensor_uuid": ["LIBRA_Meter_007"], "usage": 1328788, "eui": 89.0, "unit": "kWh", "eui_annual": 89.0}, "heat": {"sensor_label": ["Library", "Library", "Library"], "sensor_uuid": ["LIBRA_Meter_025", "LIBRA_Meter_030", "LIBRA_Meter_039"], "usage": 15309.0, "eui": 1.0, "unit": "MWh", "eui_annual": 1.0}, "water": {"sensor_label": ["Library"], "sensor_uuid": ["LIBRA_Meter_018"], "usage": 5562.55, "eui": 0.37, "unit": "m3", "eui_annual": 0.37}}, {"building_code": "PRESC", "building_name": "Pre-School Centre", "usage": "Non Res", "year_built": 1994, "floor_area": 847, "zone": "South Campus", "maze_map_label": [2973], "gas": {"sensor_label": ["Pre-School Centre"], "sensor_uuid": ["PRESC_Meter_003"], "usage": 14172.3, "eui": 17.0, "unit": "m3", "eui_annual": 17.0}, "electricity": {"sensor_label": ["Pre-School Centre"], "sensor_uuid": ["PRESC_Meter_004"], "usage": 1698885.0, "eui": 2000.0, "unit": "kWh", "eui_annual": 2000.0}, "heat": {"sensor_label": [], "sensor_uuid": [], "usage": null, "eui": null, "unit": "MWh", "eui_annual": null}, "water": {"sensor_label": [], "sensor_uuid": [], "usage": null, "eui": null, "unit": "m3", "eui_annual": null}}, {"building_code": "LEC03", "building_name": "LEC 3", "usage": "Non Res", "year_built": 2007, "floor_area": 2932, "zone": "South Campus", "maze_map_label": [1005698], "gas": {"sensor_label": [], "sensor_uuid": [], "usage": null, "eui": null, "unit": "m3", "eui_annual": null}, "electricity": {"sensor_label": [], "sensor_uuid": [], "usage": null, "eui": null, "unit": "kWh", "eui_annual": null}, "heat": {"sensor_label": ["LEC 3"], "sensor_uuid": ["LEC03_Meter_021"], "usage": 0, "eui": 0.0, "unit": "MWh", "eui_annual": 0.0}, "water": {"sensor_label": [], "sensor_uuid": [], "usage": null, "eui": null, "unit": "m3", "eui_annual": null}}, {"building_code": "LEC12", "building_name": "LEC 1 & 2", "usage": "Non Res", "year_built": 1969, "floor_area": 10145, "zone": "South Campus", "maze_map_label": [2790], "gas": {"sensor_label": [], "sensor_uuid": [], "usage": null, "eui": null, "unit": "m3", "eui_annual": null}, "electricity": {"sensor_label": [], "sensor_uuid": [], "usage": null, "eui": null, "unit": "kWh", "eui_annual": null}, "heat": {"sensor_label": ["LEC 1 & 2", "LEC 1 & 2", "LEC 1 & 2", "LEC 1 & 2"], "sensor_uuid": ["LEC12_Meter_002", "LEC12_Meter_013", "LEC12_Meter_016", "LEC12_Meter_027"], "usage": 5822.0, "eui": 0.57, "unit": "MWh", "eui_annual": 0.57}, "water": {"sensor_label": [], "sensor_uuid": [], "usage": null, "eui": null, "unit": "m3", "eui_annual": null}}, {"building_code": "FYLDC", "building_name": "Fylde College", "usage": "Split Use", "year_built": 1974, "floor_area": 5742, "zone": "South Campus", "maze_map_label": [2780], "gas": {"sensor_label": [], "sensor_uuid": [], "usage": null, "eui": null, "unit": "m3", "eui_annual": null}, "electricity": {"sensor_label": ["Fylde College"], "sensor_uuid": ["FYLDC_Meter_004"], "usage": 287458, "eui": 50.0, "unit": "kWh", "eui_annual": 50.0}, "heat": {"sensor_label": ["Fylde College", "Fylde College"], "sensor_uuid": ["FYLDC_Meter_002", "FYLDC_Meter_007"], "usage": 4019.0, "eui": 0.7, "unit": "MWh", "eui_annual": 0.7}, "water": {"sensor_label": ["Fylde College"], "sensor_uuid": ["FYLDC_Meter_000"], "usage": 2850.83, "eui": 0.5, "unit": "m3", "eui_annual": 0.5}}, {"building_code": "MGMTS", "building_name": "Management School", "usage": "Non Res", "year_built": 1974, "floor_area": 16782, "zone": "South Campus", "maze_map_label": [2807], "gas": {"sensor_label": [], "sensor_uuid": [], "usage": null, "eui": null, "unit": "m3", "eui_annual": null}, "electricity": {"sensor_label": ["Management School"], "sensor_uuid": ["MGMTS_Meter_035"], "usage": 316887.0, "eui": 19.0, "unit": "kWh", "eui_annual": 19.0}, "heat": {"sensor_label": ["Management School", "Management School", "Management School"], "sensor_uuid": ["MGMTS_Meter_001", "MGMTS_Meter_007", "MGMTS_Meter_011"], "usage": 1375.9, "eui": 0.082, "unit": "MWh", "eui_annual": 0.082}, "water": {"sensor_label": [], "sensor_uuid": [], "usage": null, "eui": null, "unit": "m3", "eui_annual": null}}, {"building_code": "SANDT", "building_name": "Science and Technology", "usage": "Non Res", "year_built": 1972, "floor_area": 7349, "zone": "South Campus", "maze_map_label": [2786], "gas": {"sensor_label": ["Science and Technology"], "sensor_uuid": ["SANDT_Meter_007"], "usage": 0, "eui": 0.0, "unit": "m3", "eui_annual": 0.0}, "electricity": {"sensor_label": ["Science and Technology"], "sensor_uuid": ["SANDT_Meter_000"], "usage": 708513, "eui": 96.0, "unit": "kWh", "eui_annual": 96.0}, "heat": {"sensor_label": ["Science and Technology", "Science and Technology"], "sensor_uuid": ["SANDT_Meter_002", "SANDT_Meter_010"], "usage": 1296.0, "eui": 0.18, "unit": "MWh", "eui_annual": 0.18}, "water": {"sensor_label": [], "sensor_uuid": [], "usage": null, "eui": null, "unit": "m3", "eui_annual": null}}, {"building_code": "WHEBG", "building_name": "Whewell Building", "usage": "Unknown", "year_built": null, "floor_area": 842, "zone": "South Campus", "maze_map_label": [2897], "gas": {"sensor_label": [], "sensor_uuid": [], "usage": null, "eui": null, "unit": "m3", "eui_annual": null}, "electricity": {"sensor_label": ["Whewell Building"], "sensor_uuid": ["WHEBG_Meter_000"], "usage": 38181, "eui": 45.0, "unit": "kWh", "eui_annual": 45.0}, "heat": {"sensor_label": [], "sensor_uuid": [], "usage": null, "eui": null, "unit": "MWh", "eui_annual": null}, "water": {"sensor_label": [], "sensor_uuid": [], "usage": null, "eui": null, "unit": "m3", "eui_annual": null}}, {"building_code": "GFXBG", "building_name": "George Fox Building", "usage": "Split Use", "year_built": 1993, "floor_area": 5360, "zone": "South Campus", "maze_map_label": [2894], "gas": {"sensor_label": [], "sensor_uuid": [], "usage": null, "eui": null, "unit": "m3", "eui_annual": null}, "electricity": {"sensor_label": ["George Fox Building"], "sensor_uuid": ["GFXBG_Meter_000"], "usage": 315019, "eui": 59.0, "unit": "kWh", "eui_annual": 59.0}, "heat": {"sensor_label": ["George Fox Building", "George Fox Building", "George Fox Building"], "sensor_uuid": ["GFXBG_Meter_003", "GFXBG_Meter_006", "GFXBG_Meter_009"], "usage": 3592.0, "eui": 0.67, "unit": "MWh", "eui_annual": 0.67}, "water": {"sensor_label": ["George Fox Building"], "sensor_uuid": ["GFXBG_Meter_001"], "usage": 5776.05, "eui": 1.1, "unit": "m3", "eui_annual": 1.1}}, {"building_code": "PCROU", "building_name": "Grizedale College, Roughlee (16)", "usage": "Residential", "year_built": 1993, "floor_area": 439, "zone": "South Campus", "maze_map_label": [3028], "gas": {"sensor_label": [], "sensor_uuid": [], "usage": null, "eui": null, "unit": "m3", "eui_annual": null}, "electricity": {"sensor_label": [], "sensor_uuid": [], "usage": null, "eui": null, "unit": "kWh", "eui_annual": null}, "heat": {"sensor_label": ["Pendle College", "Pendle College"], "sensor_uuid": ["PCROU_Meter_001", "PCROU_Meter_004"], "usage": 3478.0, "eui": 7.9, "unit": "MWh", "eui_annual": 7.9}, "water": {"sensor_label": [], "sensor_uuid": [], "usage": null, "eui": null, "unit": "m3", "eui_annual": null}}, {"building_code": "INF21", "building_name": "InfoLab21", "usage": "Non Res", "year_built": 2005, "floor_area": 5800, "zone": "South Campus", "maze_map_label": [2893], "gas": {"sensor_label": ["InfoLab21"], "sensor_uuid": ["INF21_Meter_000"], "usage": 49357, "eui": 8.5, "unit": "m3", "eui_annual": 8.5}, "electricity": {"sensor_label": ["InfoLab21"], "sensor_uuid": ["INF21_Meter_002"], "usage": 0, "eui": 0.0, "unit": "kWh", "eui_annual": 0.0}, "heat": {"sensor_label": [], "sensor_uuid": [], "usage": null, "eui": null, "unit": "MWh", "eui_annual": null}, "water": {"sensor_label": [], "sensor_uuid": [], "usage": null, "eui": null, "unit": "m3", "eui_annual": null}}, {"building_code": "LANCC", "building_name": "Lancaster Conference Centre", "usage": "Non Res", "year_built": 1989, "floor_area": 996, "zone": "South Campus", "maze_map_label": [2989], "gas": {"sensor_label": ["Lancaster House Hotel"], "sensor_uuid": ["LANCC_Meter_002"], "usage": 0, "eui": 0.0, "unit": "m3", "eui_annual": 0.0}, "electricity": {"sensor_label": ["Lancaster House Hotel"], "sensor_uuid": ["LANCC_Meter_003"], "usage": 43749.0, "eui": 44.0, "unit": "kWh", "eui_annual": 44.0}, "heat": {"sensor_label": [], "sensor_uuid": [], "usage": null, "eui": null, "unit": "MWh", "eui_annual": null}, "water": {"sensor_label": [], "sensor_uuid": [], "usage": null, "eui": null, "unit": "m3", "eui_annual": null}}, {"building_code": "PSC00", "building_name": "PSC", "usage": "Non Res", "year_built": 2008, "floor_area": 985, "zone": "South Campus", "maze_map_label": [2895], "gas": {"sensor_label": [], "sensor_uuid": [], "usage": null, "eui": null, "unit": "m3", "eui_annual": null}, "electricity": {"sensor_label": ["PSC"], "sensor_uuid": ["PSC00_Meter_012"], "usage": 161912.0, "eui": 160.0, "unit": "kWh", "eui_annual": 160.0}, "heat": {"sensor_label": ["PSC"], "sensor_uuid": ["PSC00_Meter_002"], "usage": 373.0, "eui": 0.38, "unit": "MWh", "eui_annual": 0.38}, "water": {"sensor_label": ["PSC"], "sensor_uuid": ["PSC00_Meter_000"], "usage": 676.9, "eui": 0.69, "unit": "m3", "eui_annual": 0.69}}, {"building_code": "LICA0", "building_name": "LICA", "usage": "Non Res", "year_built": 2010, "floor_area": 5011, "zone": "North Campus", "maze_map_label": [2701], "gas": {"sensor_label": [], "sensor_uuid": [], "usage": null, "eui": null, "unit": "m3", "eui_annual": null}, "electricity": {"sensor_label": [], "sensor_uuid": [], "usage": null, "eui": null, "unit": "kWh", "eui_annual": null}, "heat": {"sensor_label": ["LICA"], "sensor_uuid": ["LICA0_Meter_010"], "usage": 337.0, "eui": 0.067, "unit": "MWh", "eui_annual": 0.067}, "water": {"sensor_label": [], "sensor_uuid": [], "usage": null, "eui": null, "unit": "m3", "eui_annual": null}}, {"building_code": "CHACA", "building_name": "Charles Carter Building", "usage": "Non Res", "year_built": 2011, "floor_area": 3835, "zone": "South Campus", "maze_map_label": [2898], "gas": {"sensor_label": [], "sensor_uuid": [], "usage": null, "eui": null, "unit": "m3", "eui_annual": null}, "electricity": {"sensor_label": ["Charles Carter Building"], "sensor_uuid": ["CHACA_Meter_023"], "usage": 4143643.0, "eui": 1100.0, "unit": "kWh", "eui_annual": 1100.0}, "heat": {"sensor_label": ["Charles Carter Building"], "sensor_uuid": ["CHACA_Meter_020"], "usage": 1622.0, "eui": 0.42, "unit": "MWh", "eui_annual": 0.42}, "water": {"sensor_label": [], "sensor_uuid": [], "usage": null, "eui": null, "unit": "m3", "eui_annual": null}}, {"building_code": "SPOCE", "building_name": "Sports Centre", "usage": "Non Res", "year_built": 2011, "floor_area": 8693, "zone": "North Campus", "maze_map_label": [3101], "gas": {"sensor_label": ["Sports Centre"], "sensor_uuid": ["SPOCE_Meter_017"], "usage": 0, "eui": 0.0, "unit": "m3", "eui_annual": 0.0}, "electricity": {"sensor_label": ["Sports Centre", "Sports Centre"], "sensor_uuid": ["SPOCE_Meter_024", "SPOCE_Meter_042"], "usage": 2574596.0, "eui": 300.0, "unit": "kWh", "eui_annual": 300.0}, "heat": {"sensor_label": ["Sports Centre", "Sports Centre New Extension"], "sensor_uuid": ["SPOCE_Meter_011", "SPOCE_Meter_049"], "usage": 199.0, "eui": 0.023, "unit": "MWh", "eui_annual": 0.023}, "water": {"sensor_label": [], "sensor_uuid": [], "usage": null, "eui": null, "unit": "m3", "eui_annual": null}}, {"building_code": "HRBLD", "building_name": "HR Building", "usage": "Non Res", "year_built": 1967, "floor_area": 805, "zone": "North Campus", "maze_map_label": [2699], "gas": {"sensor_label": [], "sensor_uuid": [], "usage": null, "eui": null, "unit": "m3", "eui_annual": null}, "electricity": {"sensor_label": [], "sensor_uuid": [], "usage": null, "eui": null, "unit": "kWh", "eui_annual": null}, "heat": {"sensor_label": ["HR & Security", "HR & Security"], "sensor_uuid": ["HRBLD_Meter_003", "HRBLD_Meter_006"], "usage": 3105093.3, "eui": 3900.0, "unit": "MWh", "eui_annual": 3900.0}, "water": {"sensor_label": ["HR & Security"], "sensor_uuid": ["HRBLD_Meter_000"], "usage": 0.01, "eui": 1.2e-05, "unit": "m3", "eui_annual": 1.2e-05}}, {"building_code": "ENGI1", "building_name": "Engineering Building", "usage": "Non Res", "year_built": 2014, "floor_area": 4620, "zone": "South Campus", "maze_map_label": [2896], "gas": {"sensor_label": ["Engineering Building"], "sensor_uuid": ["ENGI1_Meter_031"], "usage": 457525.0, "eui": 99.0, "unit": "m3", "eui_annual": 99.0}, "electricity": {"sensor_label": ["Engineering Building"], "sensor_uuid": ["ENGI1_Meter_007"], "usage": 5356100.0, "eui": 1200.0, "unit": "kWh", "eui_annual": 1200.0}, "heat": {"sensor_label": ["Engineering Building", "Engineering Building"], "sensor_uuid": ["ENGI1_Meter_003", "ENGI1_Meter_030"], "usage": 2998.0, "eui": 0.65, "unit": "MWh", "eui_annual": 0.65}, "water": {"sensor_label": ["Engineering Building"], "sensor_uuid": ["ENGI1_Meter_051"], "usage": 730291.0, "eui": 160.0, "unit": "m3", "eui_annual": 160.0}}, {"building_code": "LSAEL", "building_name": "Life Sciences & Environment Laboratories", "usage": "Non Res", "year_built": 2015, "floor_area": 1352, "zone": "South Campus", "maze_map_label": [2809], "gas": {"sensor_label": ["Life Sciences & Environment Laboratories"], "sensor_uuid": ["LSAEL_Meter_028"], "usage": 15.0, "eui": 0.011, "unit": "m3", "eui_annual": 0.011}, "electricity": {"sensor_label": ["Life Sciences & Environment Laboratories"], "sensor_uuid": ["LSAEL_Meter_031"], "usage": 244316.0, "eui": 180.0, "unit": "kWh", "eui_annual": 180.0}, "heat": {"sensor_label": ["Life Sciences & Environment Laboratories", "Life Sciences & Environment Laboratories"], "sensor_uuid": ["LSAEL_Meter_020", "LSAEL_Meter_023"], "usage": 4418.913, "eui": 3.3, "unit": "MWh", "eui_annual": 3.3}, "water": {"sensor_label": [], "sensor_uuid": [], "usage": null, "eui": null, "unit": "m3", "eui_annual": null}}, {"building_code": "MFELL", "building_name": "Margaret Fell Lecture Theatre", "usage": "Non Res", "year_built": 2020, "floor_area": 699, "zone": "North Campus", "maze_map_label": [1001282], "gas": {"sensor_label": [], "sensor_uuid": [], "usage": null, "eui": null, "unit": "m3", "eui_annual": null}, "electricity": {"sensor_label": ["Margaret Fell Lectrure Theatre"], "sensor_uuid": ["MFELL_Meter_006"], "usage": 1165242.0, "eui": 1700.0, "unit": "kWh", "eui_annual": 1700.0}, "heat": {"sensor_label": ["Margaret Fell Lectrure Theatre"], "sensor_uuid": ["MFELL_Meter_000"], "usage": 0, "eui": 0.0, "unit": "MWh", "eui_annual": 0.0}, "water": {"sensor_label": ["Margaret Fell Lectrure Theatre"], "sensor_uuid": ["MFELL_Meter_005"], "usage": 0.0, "eui": 0.0, "unit": "m3", "eui_annual": 0.0}}]